autocvd/__init__.py
autocvd/main.py
autocvd/nvidia_smi_calls.py
autocvd/utils.py
autocvd-0.2.1.dist-info/METADATA
autocvd-0.2.1.dist-info/WHEEL
autocvd-0.2.1.dist-info/entry_points.txt
autocvd-0.2.1.dist-info/licenses/LICENSE
autocvd-0.2.1.dist-info/RECORD
