Metadata-Version: 2.1
Name: autocvd
Version: 0.2.1
Summary: A tool for setting CUDA_VISIBLE_DEVICES based on utilization
Project-URL: Homepage, https://github.com/jonasricker/autocvd
Project-URL: Bug Tracker, https://github.com/jonasricker/autocvd/issues
License-File: LICENSE
Classifier: Development Status :: 3 - Alpha
Classifier: License :: OSI Approved :: MIT License
Classifier: Operating System :: OS Independent
Classifier: Programming Language :: Python
Classifier: Programming Language :: Python :: 3
Classifier: Programming Language :: Python :: 3.7
Classifier: Programming Language :: Python :: 3.8
Classifier: Programming Language :: Python :: 3.9
Classifier: Programming Language :: Python :: 3.10
Classifier: Programming Language :: Python :: 3.11
Classifier: Topic :: Scientific/Engineering
Requires-Python: >=3.7
